gabby/__init__.py
gabby/controller.py
gabby/decorators.py
gabby/gabby.py
gabby/message.py
gabby/node.py
gabby/receiver.py
gabby/settings.py
gabby/topic.py
gabby/transmitter.py
gabby/udp_receiver.py
gabby/udp_transmitter.py
gabby-0.1.0.dist-info/METADATA
gabby-0.1.0.dist-info/RECORD
gabby-0.1.0.dist-info/WHEEL
gabby-0.1.0.dist-info/top_level.txt
