Metadata-Version: 2.1
Name: gabby
Version: 0.1.0
Summary: A simple controller for message queue pipelines
Home-page: https://github.com/luanguimaraesla/gabby
Author: Luan Guimarães Lacerda
Author-email: luan@live.in
License: MIT License
Keywords: iot,mosquitto,mqtt,mqttsn,message,queue,pipeline,multiprocessing
Platform: UNKNOWN
Classifier: Development Status :: 3 - Alpha
Classifier: Intended Audience :: Developers
Classifier: Operating System :: POSIX
Classifier: Programming Language :: Python
Classifier: Programming Language :: Python :: 3.6
Classifier: Topic :: Software Development :: Libraries
Provides-Extra: dev
Provides-Extra: docs
Requires-Dist: paho-mqtt
Requires-Dist: mqttsn
Provides-Extra: dev
Requires-Dist: pytest; extra == 'dev'
Requires-Dist: pytest-cov; extra == 'dev'
Requires-Dist: coverage; extra == 'dev'
Requires-Dist: flake8; extra == 'dev'
Requires-Dist: bumpversion; extra == 'dev'
Provides-Extra: docs
Requires-Dist: docutils; extra == 'docs'
Requires-Dist: sphinx-autobuild; extra == 'docs'
